{
  "enabled": true,
  "neededInstalledMods": [],
  "neededUninstalledMods": [],
  "spawns": [
    {
      "id": "oricorio-1",
      "pokemon": "oricorio dance_style=baile",
      "presets": [
        "natural"
      ],
      "type": "pokemon",
      "spawnablePositionType": "grounded",
      "bucket": "uncommon",
      "level": "16-41",
      "weight": 10.0,
      "condition": {
        "minSkyLight": 8,
        "maxSkyLight": 15,
        "timeRange": "0-5999",
        "biomes": [
          "#cobblemon:is_floral"
        ]
      }
    },
    {
      "id": "oricorio-2",
      "pokemon": "oricorio dance_style=pom-pom",
      "presets": [
        "natural"
      ],
      "type": "pokemon",
      "spawnablePositionType": "grounded",
      "bucket": "uncommon",
      "level": "16-41",
      "weight": 10.0,
      "condition": {
        "minSkyLight": 8,
        "maxSkyLight": 15,
        "timeRange": "6000-11999",
        "biomes": [
          "#cobblemon:is_floral"
        ]
      }
    },
    {
      "id": "oricorio-3",
      "pokemon": "oricorio dance_style=pau",
      "presets": [
        "natural"
      ],
      "type": "pokemon",
      "spawnablePositionType": "grounded",
      "bucket": "uncommon",
      "level": "16-41",
      "weight": 10.0,
      "condition": {
        "minSkyLight": 8,
        "maxSkyLight": 15,
        "timeRange": "12000-17999",
        "biomes": [
          "#cobblemon:is_floral"
        ]
      }
    },
    {
      "id": "oricorio-4",
      "pokemon": "oricorio dance_style=sensu",
      "presets": [
      ],
      "type": "pokemon",
      "spawnablePositionType": "grounded",
      "bucket": "uncommon",
      "level": "16-41",
      "weight": 10.0,
      "condition": {
        "minSkyLight": 8,
        "maxSkyLight": 15,
        "timeRange": "18000-23999",
        "biomes": [
          "#cobblemon:is_floral"
        ]
      }
    }
  ]
}